MANIFEST.in
Makefile
README.md
README_PIP.rst
requirements.txt
setup.cfg
setup.py
pyredatam/__init__.py
pyredatam/cpv2010arg.py
pyredatam/pyredatam.py
pyredatam/utils.py
pyredatam.egg-info/PKG-INFO
pyredatam.egg-info/SOURCES.txt
pyredatam.egg-info/dependency_links.txt
pyredatam.egg-info/not-zip-safe
pyredatam.egg-info/requires.txt
pyredatam.egg-info/top_level.txt
tests/__init__.py
tests/test_cpv2010arg.py
tests/test_pyredatam.py