Metadata-Version: 1.1
Name: pyredatam
Version: 0.0.12
Summary: Genera consultas REDATAM en python.
Home-page: https://github.com/abenassi/pyredatam
Author: Agustín Benassi
Author-email: agusbenassi@gmail.com
License: GPLv3+
Keywords: pyredatam
Platform: UNKNOWN
Classifier: Development Status :: 2 - Pre-Alpha
Classifier: Intended Audience :: Developers
Classifier: License :: OSI Approved :: GNU General Public License v3 or later (GPLv3+)
Classifier: Natural Language :: English
Classifier: Programming Language :: Python :: 2
Classifier: Programming Language :: Python :: 2.7
